brain_observatory_utilities/__init__.py
brain_observatory_utilities/datasets/__init__.py
brain_observatory_utilities/datasets/behavior/__init__.py
brain_observatory_utilities/datasets/behavior/data_access.py
brain_observatory_utilities/datasets/behavior/data_formatting.py
brain_observatory_utilities/datasets/electrophysiology/__init__.py
brain_observatory_utilities/datasets/electrophysiology/ccf_tools.py
brain_observatory_utilities/datasets/electrophysiology/receptive_field_mapping.py
brain_observatory_utilities/datasets/electrophysiology/utilities.py
brain_observatory_utilities/datasets/optical_physiology/__init__.py
brain_observatory_utilities/datasets/optical_physiology/data_access.py
brain_observatory_utilities/datasets/optical_physiology/data_formatting.py
brain_observatory_utilities/datasets/stimulus_alignment/__init__.py
brain_observatory_utilities/datasets/stimulus_alignment/data_formatting.py
brain_observatory_utilities/plotting/__init__.py
brain_observatory_utilities/plotting/behavior_plots.py
brain_observatory_utilities/plotting/ophys_plots.py
brain_observatory_utilities/plotting/plot_utils.py
brain_observatory_utilities/utilities/__init__.py
brain_observatory_utilities/utilities/general_utilities.py
brain_observatory_utilities/utilities/trial_utilities.py
brain_observatory_utilities-0.5.1.dist-info/licenses/LICENSE
brain_observatory_utilities-0.5.1.dist-info/METADATA
brain_observatory_utilities-0.5.1.dist-info/WHEEL
brain_observatory_utilities-0.5.1.dist-info/top_level.txt
brain_observatory_utilities-0.5.1.dist-info/RECORD
