Metadata-Version: 2.4
Name: brain_observatory_utilities
Version: 0.5.1
Summary: Utilities for analyzing, manipulating and visualizing data for Brain Observatory projects
Home-page: https://github.com/AllenInstitute/mindscope_utilities
Author: Allen Institute
Author-email: marinag@alleninstitute.org, corbettb@alleninstitute.org, michaelbu@alleninstitute.org, clark.roll@alleninstitute.org
License: Allen Institute
Classifier: Development Status :: 3 - Alpha
Classifier: Intended Audience :: Science/Research
Classifier: Topic :: Scientific/Engineering :: Bio-Informatics
Classifier: License :: Other/Proprietary License
Classifier: Natural Language :: English
Classifier: Programming Language :: Python :: 3.8
License-File: LICENSE
Requires-Dist: flake8
Requires-Dist: pytest
Requires-Dist: allensdk
Dynamic: author
Dynamic: author-email
Dynamic: classifier
Dynamic: home-page
Dynamic: license
Dynamic: license-file
Dynamic: requires-dist
Dynamic: summary
